{"index.md":"Ca6pgAwc","indexjsdoc.md":"B9hk-jNx","pages_benchmarking.md":"C6zeJ_If","pages_builder.md":"DZFKBm8H","pages_cli.md":"B2Onr91O","pages_codeanalysis.md":"B-yfr48B","pages_configuration.md":"Di2zpXCC","pages_essupport.md":"BwdyZAwB","pages_extensibility_customservermiddleware.md":"CGf7PTJm","pages_extensibility_customtasks.md":"S3cHQgXI","pages_extensibility_projectshims.md":"CLJaOc0L","pages_faq.md":"BPVmsclZ","pages_filesystem.md":"BwRAHKER","pages_gettingstarted.md":"Da1Q9z7J","pages_openui5.md":"Dd5qkylq","pages_overview.md":"B5UfQr1H","pages_privacy.md":"hMi8EPUy","pages_project.md":"DbUERBx0","pages_sapui5.md":"uc2JUR1U","pages_server.md":"DUi4SUJc","pages_troubleshooting.md":"B7Z2CXFi","pages_workspace.md":"BMwdirNg","updates_migrate-v1.md":"CjRU9uph","updates_migrate-v2.md":"BEpPzmXK","updates_migrate-v3.md":"CARZXNtL","updates_migrate-v4.md":"Gzaixct9"}
