{"index.md":"BEc72xnp","indexjsdoc.md":"DPOV4MTP","pages_benchmarking.md":"Bu2Pu1g4","pages_builder.md":"V1I0lKEs","pages_cli.md":"eM3X58qj","pages_codeanalysis.md":"CJLxi5Is","pages_configuration.md":"BjS-c8Pb","pages_essupport.md":"B_UmIU1g","pages_extensibility_customservermiddleware.md":"B8MCYxF5","pages_extensibility_customtasks.md":"JlRzuey1","pages_extensibility_projectshims.md":"CYK5nhby","pages_faq.md":"CU99zKAE","pages_filesystem.md":"Cw9ESOvt","pages_gettingstarted.md":"PrSY_l0I","pages_openui5.md":"6K-hKnCn","pages_overview.md":"BoQwp6_b","pages_privacy.md":"DBGFDSEp","pages_project.md":"DUsfNq21","pages_sapui5.md":"BJrlliM2","pages_server.md":"BM_EEIUo","pages_troubleshooting.md":"BGEj_gZh","pages_workspace.md":"D5EuYTPD","updates_migrate-v1.md":"DhSesLKp","updates_migrate-v2.md":"CJtfNNWh","updates_migrate-v3.md":"wmkPqI9C","updates_migrate-v4.md":"C2Z0kIgZ"}
